optiquantfolio/__init__.py
optiquantfolio/capm.py
optiquantfolio/data_fetcher.py
optiquantfolio/genetic_algorithm.py
optiquantfolio/hrp.py
optiquantfolio/minimum_variance.py
optiquantfolio/portfolio_optimizer.py
optiquantfolio/robust_optimization.py
optiquantfolio/stochastic_control.py
optiquantfolio/treynor_ratio.py
optiquantfolio/utils.py
portfolio_optimizer/__init__.py
portfolio_optimizer/capm.py
portfolio_optimizer/data_fetcher.py
portfolio_optimizer/genetic_algorithm.py
portfolio_optimizer/hrp.py
portfolio_optimizer/minimum_variance.py
portfolio_optimizer/portfolio_optimizer.py
portfolio_optimizer/robust_optimization.py
portfolio_optimizer/stochastic_control.py
portfolio_optimizer/treynor_ratio.py
portfolio_optimizer/utils.py
Optiquantfolio-0.1.1.dist-info/LICENSE
Optiquantfolio-0.1.1.dist-info/METADATA
Optiquantfolio-0.1.1.dist-info/WHEEL
Optiquantfolio-0.1.1.dist-info/top_level.txt
Optiquantfolio-0.1.1.dist-info/RECORD
