Metadata-Version: 2.1
Name: Optiquantfolio
Version: 0.1.1
Summary: A comprehensive AI-based library for portfolio optimization
Home-page: https://github.com/praetorian2710/OptiQuant
Author: Jotiraditya Banerjee
Author-email: joti.ban.2710@gmail.com
Classifier: Programming Language :: Python :: 3
Classifier: License :: OSI Approved :: MIT License
Classifier: Operating System :: OS Independent
Requires-Python: >=3.6
License-File: LICENSE
Requires-Dist: numpy
Requires-Dist: pandas
Requires-Dist: scipy
Requires-Dist: scikit-learn
Requires-Dist: deap
Requires-Dist: yfinance
